django_page_hits/__init__.py
django_page_hits/admin.py
django_page_hits/apps.py
django_page_hits/middleware.py
django_page_hits/models.py
django_page_hits/migrations/0001_initial.py
django_page_hits/migrations/0002_auto_20201012_1923.py
django_page_hits/migrations/0003_alter_pagehit_id.py
django_page_hits/migrations/__init__.py
django_page_hits/tests/MockRequest.py
django_page_hits/tests/__init__.py
django_page_hits/tests/settings.py
django_page_hits/tests/test_django_page_hits.py
django_page_hits-0.2.0.dist-info/AUTHORS.rst
django_page_hits-0.2.0.dist-info/LICENSE
django_page_hits-0.2.0.dist-info/METADATA
django_page_hits-0.2.0.dist-info/WHEEL
django_page_hits-0.2.0.dist-info/top_level.txt
django_page_hits-0.2.0.dist-info/RECORD
