Metadata-Version: 2.1
Name: django_page_hits
Version: 0.2.0
Summary: A middleware which stores the records of page view counts
Home-page: https://github.com/amritghimire/django_page_hits
Author: Amrit Ghimire
Author-email: mail@amritghimire.com
License: MIT license
Keywords: django_page_hits
Classifier: Development Status :: 2 - Pre-Alpha
Classifier: Intended Audience :: Developers
Classifier: License :: OSI Approved :: MIT License
Classifier: Natural Language :: English
Classifier: Programming Language :: Python :: 3
Classifier: Programming Language :: Python :: 3.5
Classifier: Programming Language :: Python :: 3.6
Classifier: Programming Language :: Python :: 3.7
Classifier: Programming Language :: Python :: 3.8
Requires-Python: >=3.5
License-File: LICENSE
License-File: AUTHORS.rst
